{
  "target": "https://example.com",
  "strategy": [
    "sql_injection"
  ],
  "extra": "--dry-run",
  "started_at": "2025-11-06T16:31:37.700213",
  "ended_at": "2025-11-06T16:31:40.725828",
  "results": [
    {
      "poc": "sql_injection",
      "status": "ok",
      "result": {
        "job_id": "b79a9b69abff",
        "target": "https://example.com",
        "poc_extra": "--dry-run --poc=sql_injection",
        "status": "error",
        "confidence": 0.2,
        "votes": [
          "error",
          "error"
        ],
        "attempts": [
          {
            "attempt_id": "3a6fd117318d",
            "container": "axs_sandbox_3a6fd117318d",
            "exit_code": -2,
            "output": "SDK runner error: 404 Client Error for http+docker://localhost/v1.44/containers/create?name=axs_sandbox_3a6fd117318d: Not Found (\"No such image: python:3.11-slim\")",
            "output_hash": "e3b0c44298fc1c149afbf4c8996fb92427ae41e4649b934ca495991b7852b855",
            "duration": 0.008,
            "attempt": 1
          },
          {
            "attempt_id": "6f731eeaea37",
            "container": "axs_sandbox_6f731eeaea37",
            "exit_code": -2,
            "output": "SDK runner error: 404 Client Error for http+docker://localhost/v1.44/containers/create?name=axs_sandbox_6f731eeaea37: Not Found (\"No such image: python:3.11-slim\")",
            "output_hash": "e3b0c44298fc1c149afbf4c8996fb92427ae41e4649b934ca495991b7852b855",
            "duration": 0.003,
            "attempt": 2
          }
        ],
        "timestamp": "2025-11-06T16:31:40.722069",
        "notes": [],
        "_result_file": "/app/data/results/https_example.com_20251106163140_64ca149d8c7c.json"
      }
    }
  ]
}